{
  "provider": "PolyU APSS JS3250 Applied Social Sciences Curriculum 2026/27",
  "academicYear": "2026",
  "sourceUrl": "https://www.polyu.edu.hk/apss/docdrive/epro/JS3250_Programme%20Curriculum%20for%20CMS%20e-Pro_2627.pdf",
  "officialUrl": "https://www.polyu.edu.hk/study/ug/jupas/2026/js3250",
  "supplements": [
    {
      "universityCode": "POLYU",
      "programmeCode": "JS3250",
      "majorName": "Social Work",
      "sourceUrl": "https://www.polyu.edu.hk/apss/docdrive/epro/JS3250_Programme%20Curriculum%20for%20CMS%20e-Pro_2627.pdf",
      "officialUrl": "https://www.polyu.edu.hk/study/ug/jupas/2026/js3250",
      "courses": [
        { "code": "COMP1004", "title": "Introduction to AI and Data Analytics", "credits": 2, "group": "General University Requirements" },
        { "code": "MM1031", "title": "Introduction to Innovation and Entrepreneurship", "credits": 1, "group": "General University Requirements" },
        { "code": "APSS1L01", "title": "Tomorrow's Leaders", "credits": 3, "group": "General University Requirements" },
        { "code": "APSS111", "title": "Introduction to Psychology", "credits": 3, "group": "Common underpinning subjects" },
        { "code": "APSS112", "title": "Introduction to Sociology", "credits": 3, "group": "Common underpinning subjects" },
        { "code": "APSS118", "title": "Self Understanding and Communication Skills", "credits": 3, "group": "Common underpinning subjects" },
        { "code": "APSS120", "title": "Introduction to Social Services in Hong Kong", "credits": 3, "group": "Common underpinning subjects" },
        { "code": "APSS2200", "title": "The Art of Reasoning", "credits": 3, "group": "Common underpinning subjects" },
        { "code": "APSS231", "title": "Hong Kong Society", "credits": 3, "group": "Common underpinning subjects" },
        { "code": "CLC2261P", "title": "Chinese Communication for Social Sciences", "credits": 2, "group": "Discipline-specific language subjects" },
        { "code": "ELC3621", "title": "Professional English for Social Sciences", "credits": 2, "group": "Discipline-specific language subjects" },
        { "code": "APSS1130", "title": "Introduction to Politics", "credits": 3, "group": "Common Year One / free elective" },
        { "code": "APSS116", "title": "Introduction to Social Work", "credits": 3, "group": "Social Work professional core" },
        { "code": "APSS261", "title": "Community Field Study", "credits": 3, "group": "Social Work professional core" },
        { "code": "APSS2681", "title": "Generic Social Work Practice with Individuals and Families", "credits": 3, "group": "Social Work professional core" },
        { "code": "APSS2682", "title": "Generic Social Work Practice with Groups, Organizations and Communities", "credits": 3, "group": "Social Work professional core" },
        { "code": "APSS3610", "title": "Generic Social Work Practice Workshop", "credits": 3, "group": "Social Work professional core" },
        { "code": "APSS3960", "title": "Social Work Practice in Mental Health", "credits": 3, "group": "Social Work professional core" },
        { "code": "APSS4610", "title": "Integrative Seminar", "credits": 3, "group": "Social Work professional core" },
        { "code": "APSS4613", "title": "Social Work Theory & Practice: Working with Individuals", "credits": 3, "group": "Social Work professional core" },
        { "code": "APSS4614", "title": "Social Work Theory & Practice: Working with Families & Systems", "credits": 3, "group": "Social Work professional core" },
        { "code": "APSS4615", "title": "Social Work Theory & Practice: Working with Communities", "credits": 3, "group": "Social Work professional core" },
        { "code": "APSS225", "title": "Human Behaviour and Social Environment", "credits": 3, "group": "Social Science core" },
        { "code": "APSS3201", "title": "Social Structure and Social Theory", "credits": 3, "group": "Social Science core" },
        { "code": "APSS331", "title": "Management in Human Services", "credits": 3, "group": "Social Science core" },
        { "code": "APSS343", "title": "Philosophy of Welfare", "credits": 3, "group": "Social Science core" },
        { "code": "APSS345", "title": "Social Research Methods", "credits": 3, "group": "Social Science core" },
        { "code": "APSS451", "title": "Social Policy", "credits": 3, "group": "Social Science core" },
        { "code": "APSS454", "title": "Legal Aspects of Human Services", "credits": 3, "group": "Social Science core" },
        { "code": "APSS366", "title": "Family and Social Work", "credits": 3, "group": "Social Work integrative electives" },
        { "code": "APSS369", "title": "Social Work with Drug abusers", "credits": 3, "group": "Social Work integrative electives" },
        { "code": "APSS370", "title": "Youth and Social Work", "credits": 3, "group": "Social Work integrative electives" },
        { "code": "APSS391", "title": "Aging and Social Work", "credits": 3, "group": "Social Work integrative electives" },
        { "code": "APSS3910", "title": "Child Maltreatment and Protection", "credits": 3, "group": "Social Work integrative electives" },
        { "code": "APSS3911", "title": "Social Work in School Settings", "credits": 3, "group": "Social Work integrative electives" },
        { "code": "APSS3912", "title": "Diversity and Inclusion in Social Work", "credits": 3, "group": "Social Work integrative electives" },
        { "code": "APSS3913", "title": "Sustainability and Social Work", "credits": 3, "group": "Social Work integrative electives" },
        { "code": "APSS3914", "title": "Offender, Victim, and Social Work: A Crime Prevention Perspective", "credits": 3, "group": "Social Work integrative electives" },
        { "code": "APSS3915", "title": "Vulnerable Populations and Health in Social Work", "credits": 3, "group": "Social Work integrative electives" },
        { "code": "APSS2700", "title": "Preparatory Workshop (I)", "credits": 0, "courseType": "internship", "group": "Clinical/Field subjects" },
        { "code": "APSS3700", "title": "Preparatory Workshop (II)", "credits": 0, "courseType": "internship", "group": "Clinical/Field subjects" },
        { "code": "APSS3793", "title": "Fieldwork I", "credits": 6, "courseType": "internship", "group": "Clinical/Field subjects" },
        { "code": "APSS4693", "title": "Fieldwork II", "credits": 9, "courseType": "internship", "group": "Clinical/Field subjects" },
        { "code": "APSS463", "title": "Capstone Project", "credits": 3, "group": "Capstone Project" }
      ]
    },
    {
      "universityCode": "POLYU",
      "programmeCode": "JS3250",
      "majorName": "Social Policy and Social Entrepreneurship",
      "sourceUrl": "https://www.polyu.edu.hk/apss/docdrive/epro/JS3250_Programme%20Curriculum%20for%20CMS%20e-Pro_2627.pdf",
      "officialUrl": "https://www.polyu.edu.hk/study/ug/jupas/2026/js3250",
      "courses": [
        { "code": "COMP1004", "title": "Introduction to AI and Data Analytics", "credits": 2, "group": "General University Requirements" },
        { "code": "MM1031", "title": "Introduction to Innovation and Entrepreneurship", "credits": 1, "group": "General University Requirements" },
        { "code": "APSS1L01", "title": "Tomorrow's Leaders", "credits": 3, "group": "General University Requirements" },
        { "code": "APSS111", "title": "Introduction to Psychology", "credits": 3, "group": "Common underpinning subjects" },
        { "code": "APSS112", "title": "Introduction to Sociology", "credits": 3, "group": "Common underpinning subjects" },
        { "code": "APSS118", "title": "Self Understanding and Communication Skills", "credits": 3, "group": "Common underpinning subjects" },
        { "code": "APSS120", "title": "Introduction to Social Services in Hong Kong", "credits": 3, "group": "Common underpinning subjects" },
        { "code": "APSS2200", "title": "The Art of Reasoning", "credits": 3, "group": "Common underpinning subjects" },
        { "code": "APSS231", "title": "Hong Kong Society", "credits": 3, "group": "Common underpinning subjects" },
        { "code": "CLC2261P", "title": "Chinese Communication for Social Sciences", "credits": 2, "group": "Discipline-specific language subjects" },
        { "code": "ELC3621", "title": "Professional English for Social Sciences", "credits": 2, "group": "Discipline-specific language subjects" },
        { "code": "APSS116", "title": "Introduction to Social Work", "credits": 3, "group": "Common Year One / free elective" },
        { "code": "AF1605", "title": "Introduction to Economics", "credits": 3, "group": "Professional core" },
        { "code": "APSS1130", "title": "Introduction to Politics", "credits": 3, "group": "Professional core" },
        { "code": "APSS323", "title": "Government and Public Administration", "credits": 3, "group": "Professional core" },
        { "code": "APSS3230", "title": "Theories of Social Policy", "credits": 3, "group": "Professional core" },
        { "code": "APSS3232", "title": "Social Planning and Policy Making Process", "credits": 3, "group": "Professional core" },
        { "code": "APSS3233", "title": "Research for Policy and Organizations", "credits": 3, "group": "Professional core" },
        { "code": "APSS331", "title": "Management in Human Services", "credits": 3, "group": "Professional core" },
        { "code": "APSS345", "title": "Social Research Methods", "credits": 3, "group": "Professional core" },
        { "code": "APSS4510", "title": "Corporate Social Responsibility", "credits": 3, "group": "Professional core" },
        { "code": "APSS4511", "title": "Social Entrepreneurship and Enterprises", "credits": 3, "group": "Professional core" },
        { "code": "APSS3221", "title": "Civil Society and Governance", "credits": 3, "group": "Social Policy and Innovation stream electives" },
        { "code": "APSS3224", "title": "Social Capital", "credits": 3, "group": "Social Policy and Innovation stream electives" },
        { "code": "APSS3242", "title": "Understanding Diversities", "credits": 3, "group": "Social Policy and Innovation stream electives" },
        { "code": "APSS3244", "title": "Social Data Analytics", "credits": 3, "group": "Social Policy and Innovation stream electives" },
        { "code": "APSS4532", "title": "Labour and Welfare", "credits": 3, "group": "Social Policy and Innovation stream electives" },
        { "code": "APSS4533", "title": "Health and Society", "credits": 3, "group": "Social Policy and Innovation stream electives" },
        { "code": "APSS4534", "title": "Housing Issues, Challenges and Solutions", "credits": 3, "group": "Social Policy and Innovation stream electives" },
        { "code": "APSS4535", "title": "Social Innovations for Grand Challenges", "credits": 3, "group": "Social Policy and Innovation stream electives" },
        { "code": "APSS3234", "title": "Financial Planning and Management in Organizations", "credits": 3, "group": "Social Entrepreneurship stream electives" },
        { "code": "APSS3235", "title": "Media and Social Innovation", "credits": 3, "group": "Social Entrepreneurship stream electives" },
        { "code": "APSS324", "title": "Human Capital Development", "credits": 3, "group": "Social Entrepreneurship stream electives" },
        { "code": "APSS328", "title": "Programme Planning and Evaluation", "credits": 3, "group": "Social Entrepreneurship stream electives" },
        { "code": "APSS352", "title": "Marketing Strategies and Skills in Human Services", "credits": 3, "group": "Social Entrepreneurship stream electives" },
        { "code": "APSS4536", "title": "Environmental, Social and Governance Reporting and Strategy", "credits": 3, "group": "Social Entrepreneurship stream electives" },
        { "code": "APSS4537", "title": "Entrepreneurship for Global and Social Development", "credits": 3, "group": "Social Entrepreneurship stream electives" },
        { "code": "APSS454", "title": "Legal Aspects of Human Services", "credits": 3, "group": "Social Entrepreneurship stream electives" },
        { "code": "APSS3201", "title": "Social Structure and Social Theory", "credits": 3, "group": "Social Science electives" },
        { "code": "APSS3225", "title": "Media and Society", "credits": 3, "group": "Social Science electives" },
        { "code": "APSS340", "title": "Political Economy of Hong Kong", "credits": 3, "group": "Social Science electives" },
        { "code": "APSS344", "title": "Self, Culture and Society", "credits": 3, "group": "Social Science electives" },
        { "code": "APSS348", "title": "Economics and Social Problems", "credits": 3, "group": "Social Science electives" },
        { "code": "APSS4541", "title": "Justice and the Modern Social Context", "credits": 3, "group": "Social Science electives" },
        { "code": "APSS3245", "title": "Attachment for Social Policy and Social Entrepreneurship", "credits": 6, "courseType": "internship", "group": "Clinical/Field subjects" },
        { "code": "APSS3782", "title": "Attachment Workshop", "credits": 3, "courseType": "internship", "group": "Clinical/Field subjects" },
        { "code": "APSS4513", "title": "Capstone Project for Practicing Social Policy and Social Entrepreneurship", "credits": 3, "group": "Capstone Project" }
      ]
    }
  ]
}
