{
  "schemaVersion": 1,
  "schoolCode": "LINGNAN",
  "academicYear": "2026-27",
  "verifiedAt": "2026-07-14",
  "programmes": [
    {
      "programmeId": "LINGNAN-TPG-DIR-18-000444-L6",
      "status": "verified",
      "creditsRequired": 30,
      "creditUnit": "credits",
      "sourceUrl": "https://www.ln.edu.hk/econ/mide/programme-overview/programme-structure",
      "ruleReviewStatus": "verified",
      "courseGroups": [
        {
          "id": "core-courses",
          "name": "Core Courses",
          "type": "core",
          "creditsRequired": 18,
          "coursesRequired": 6,
          "ruleText": "Complete all six Core Courses (18 credits).",
          "appliesToTrackIds": [],
          "sourceUrl": "https://www.ln.edu.hk/econ/mide/programme-overview/programme-structure",
          "courses": [
            { "code": "IDE501", "name": "Microeconomics for Development", "credits": 3, "appliesToTrackIds": [], "sourceUrl": "https://www.ln.edu.hk/econ/mide/programme-overview/programme-structure" },
            { "code": "IDE502", "name": "Macroeconomics for Development", "credits": 3, "appliesToTrackIds": [], "sourceUrl": "https://www.ln.edu.hk/econ/mide/programme-overview/programme-structure" },
            { "code": "IDE503", "name": "Development Economics", "credits": 3, "appliesToTrackIds": [], "sourceUrl": "https://www.ln.edu.hk/econ/mide/programme-overview/programme-structure" },
            { "code": "IDE504", "name": "International Trade", "credits": 3, "appliesToTrackIds": [], "sourceUrl": "https://www.ln.edu.hk/econ/mide/programme-overview/programme-structure" },
            { "code": "IDE505", "name": "Current Issues in International and Development Economics", "credits": 3, "appliesToTrackIds": [], "sourceUrl": "https://www.ln.edu.hk/econ/mide/programme-overview/programme-structure" },
            { "code": "IDE515", "name": "Research Methods", "credits": 3, "appliesToTrackIds": [], "sourceUrl": "https://www.ln.edu.hk/econ/mide/programme-overview/programme-structure" }
          ]
        },
        {
          "id": "elective-courses",
          "name": "Elective Courses",
          "type": "elective",
          "creditsRequired": 12,
          "coursesRequired": 4,
          "ruleText": "Choose any four Elective Courses (12 credits). Courses marked as not offered in AY2025-26 remain part of the official elective pool.",
          "appliesToTrackIds": [],
          "sourceUrl": "https://www.ln.edu.hk/econ/mide/programme-overview/programme-structure",
          "courses": [
            { "code": "IDE506", "name": "International Money and Finance", "credits": 3, "appliesToTrackIds": [], "sourceUrl": "https://www.ln.edu.hk/econ/mide/programme-overview/programme-structure" },
            { "code": "IDE507", "name": "Globalisation and Economic Development", "credits": 3, "appliesToTrackIds": [], "sourceUrl": "https://www.ln.edu.hk/econ/mide/programme-overview/programme-structure" },
            { "code": "IDE508", "name": "The World Economy", "credits": 3, "appliesToTrackIds": [], "sourceUrl": "https://www.ln.edu.hk/econ/mide/programme-overview/programme-structure" },
            { "code": "IDE509", "name": "International Political Economy", "credits": 3, "appliesToTrackIds": [], "sourceUrl": "https://www.ln.edu.hk/econ/mide/programme-overview/programme-structure" },
            { "code": "IDE510", "name": "The Belt and Road Initiative: History, Politics, Economy and Society", "credits": 3, "appliesToTrackIds": [], "sourceUrl": "https://www.ln.edu.hk/econ/mide/programme-overview/programme-structure" },
            { "code": "IDE511", "name": "Chinese Economic Development", "credits": 3, "appliesToTrackIds": [], "sourceUrl": "https://www.ln.edu.hk/econ/mide/programme-overview/programme-structure" },
            { "code": "IDE512", "name": "Political Economy of Economic Development", "credits": 3, "appliesToTrackIds": [], "sourceUrl": "https://www.ln.edu.hk/econ/mide/programme-overview/programme-structure" },
            { "code": "IDE513", "name": "Environmental Issues and Sustainable Development", "credits": 3, "appliesToTrackIds": [], "sourceUrl": "https://www.ln.edu.hk/econ/mide/programme-overview/programme-structure" },
            { "code": "IDE514", "name": "Globalisation and Economic Integration", "credits": 3, "appliesToTrackIds": [], "sourceUrl": "https://www.ln.edu.hk/econ/mide/programme-overview/programme-structure" },
            { "code": "IDE518", "name": "Industrial Economics and Policy", "credits": 3, "appliesToTrackIds": [], "sourceUrl": "https://www.ln.edu.hk/econ/mide/programme-overview/programme-structure" },
            { "code": "IDE519", "name": "Artificial Intelligence and Digital Economy", "credits": 3, "appliesToTrackIds": [], "sourceUrl": "https://www.ln.edu.hk/econ/mide/programme-overview/programme-structure" },
            { "code": "IBF629", "name": "Selected Seminars in Economics and Finance", "credits": 3, "appliesToTrackIds": [], "sourceUrl": "https://www.ln.edu.hk/econ/mide/programme-overview/programme-structure" }
          ]
        }
      ]
    }
  ]
}
